PhyloPhlAn-3.1.1.data/scripts/phylophlan_write_default_configs.sh
phylophlan/__init__.py
phylophlan/phylophlan.py
phylophlan/phylophlan_assign_sgbs.py
phylophlan/phylophlan_draw_metagenomic.py
phylophlan/phylophlan_get_reference.py
phylophlan/phylophlan_setup_database.py
phylophlan/phylophlan_strain_finder.py
phylophlan/phylophlan_write_config_file.py
phylophlan/phylophlan_substitution_matrices/generate_matrices.sh
phylophlan/phylophlan_substitution_matrices/miqs
phylophlan/phylophlan_substitution_matrices/miqs.pkl
phylophlan/phylophlan_substitution_matrices/pfasum60
phylophlan/phylophlan_substitution_matrices/pfasum60.pkl
phylophlan/phylophlan_substitution_matrices/serialize_matrix.py
phylophlan/phylophlan_substitution_matrices/vt_scores.pl
phylophlan/phylophlan_substitution_matrices/vtml200
phylophlan/phylophlan_substitution_matrices/vtml200.pkl
phylophlan/phylophlan_substitution_matrices/vtml240
phylophlan/phylophlan_substitution_matrices/vtml240.pkl
phylophlan/phylophlan_substitution_models/phylophlan.tsv
PhyloPhlAn-3.1.1.dist-info/METADATA
PhyloPhlAn-3.1.1.dist-info/WHEEL
PhyloPhlAn-3.1.1.dist-info/entry_points.txt
PhyloPhlAn-3.1.1.dist-info/top_level.txt
PhyloPhlAn-3.1.1.dist-info/RECORD
