Metadata-Version: 2.1
Name: PhyloPhlAn
Version: 3.1.1
Summary: Precise phylogenetic analysis of microbial isolates and genomes from metagenomes
Home-page: http://github.com/biobakery/phylophlan
Author: Francesco Asnicar
Author-email: f.asnicar@unitn.it
License: license.txt
Platform: UNKNOWN
Requires-Dist: biopython
Requires-Dist: dendropy
Requires-Dist: matplotlib
Requires-Dist: numpy
Requires-Dist: pandas
Requires-Dist: seaborn
